keepmenu/__init__.py
keepmenu/__main__.py
keepmenu/_version.py
keepmenu/edit.py
keepmenu/keepmenu.py
keepmenu/menu.py
keepmenu/tokens_dotool.py
keepmenu/tokens_pynput.py
keepmenu/tokens_wtype.py
keepmenu/tokens_xdotool.py
keepmenu/tokens_ydotool.py
keepmenu/totp.py
keepmenu/type.py
keepmenu/view.py
keepmenu-1.4.4.data/data/share/doc/keepmenu/LICENSE
keepmenu-1.4.4.data/data/share/doc/keepmenu/README.md
keepmenu-1.4.4.data/data/share/doc/keepmenu/config.ini.example
keepmenu-1.4.4.data/data/share/doc/keepmenu/docs/configure.md
keepmenu-1.4.4.data/data/share/doc/keepmenu/docs/install.md
keepmenu-1.4.4.data/data/share/doc/keepmenu/docs/usage.md
keepmenu-1.4.4.data/data/share/man/man1/keepmenu.1
keepmenu-1.4.4.dist-info/METADATA
keepmenu-1.4.4.dist-info/WHEEL
keepmenu-1.4.4.dist-info/entry_points.txt
keepmenu-1.4.4.dist-info/licenses/LICENSE
keepmenu-1.4.4.dist-info/RECORD
