Metadata-Version: 2.3
Name: keepmenu
Version: 1.4.4
Summary: Dmenu frontend for Keepass databases
Project-URL: Homepage, https://github.com/firecat53/keepmenu
Author-email: Scott Hansen <tech@firecat53.net>
License: GPL-3.0
Keywords: dmenu,keepass,keepassxc,rofi,wofi
Classifier: Development Status :: 4 - Beta
Classifier: Environment :: Console
Classifier: Environment :: X11 Applications
Classifier: Intended Audience :: End Users/Desktop
Classifier: License :: OSI Approved :: GNU General Public License v3 (GPLv3)
Classifier: Programming Language :: Python
Classifier: Programming Language :: Python :: 3.7
Classifier: Programming Language :: Python :: 3.8
Classifier: Programming Language :: Python :: 3.9
Classifier: Programming Language :: Python :: 3.10
Classifier: Programming Language :: Python :: 3.11
Classifier: Programming Language :: Python :: 3.12
Classifier: Programming Language :: Python :: 3.13
Classifier: Topic :: Utilities
Requires-Dist: pykeepass>=4.0.0
Requires-Dist: pynput
